[
  {
    "item_code": "SKU005",
    "warehouse": "Work In Progress - FCD",
    "item_group": "Demo Item Group",
    "company": "Fashion Company (Demo)",
    "currency": 0,
    "stock_uom": "Nos",
    "item_name": "Sneakers",
    "opening_qty": 182,
    "opening_val": 40404,
    "opening_fifo_queue": [],
    "in_qty": 0,
    "in_val": 0,
    "out_qty": 0,
    "out_val": 0,
    "bal_qty": 182,
    "bal_val": 40404,
    "val_rate": 222,
    "reserved_stock": 0
  },
  {
    "item_code": "SKU010",
    "warehouse": "Finished Goods - FCD",
    "item_group": "Demo Item Group",
    "company": "Fashion Company (Demo)",
    "currency": 0,
    "stock_uom": "Nos",
    "item_name": "Camera",
    "opening_qty": 28,
    "opening_val": 14000,
    "opening_fifo_queue": [],
    "in_qty": 0,
    "in_val": 0,
    "out_qty": 0,
    "out_val": 0,
    "bal_qty": 28,
    "bal_val": 14000,
    "val_rate": 500,
    "reserved_stock": 0
  },
  {
    "item_code": "SKU009",
    "warehouse": "Goods In Transit - FCD",
    "item_group": "Demo Item Group",
    "company": "Fashion Company (Demo)",
    "currency": 0,
    "stock_uom": "Nos",
    "item_name": "Headphones",
    "opening_qty": 76,
    "opening_val": 53200,
    "opening_fifo_queue": [],
    "in_qty": 0,
    "in_val": 0,
    "out_qty": 0,
    "out_val": 0,
    "bal_qty": 76,
    "bal_val": 53200,
    "val_rate": 700,
    "reserved_stock": 0
  },
  {
    "item_code": "SKU007",
    "warehouse": "Goods In Transit - FCD",
    "item_group": "Demo Item Group",
    "company": "Fashion Company (Demo)",
    "currency": 0,
    "stock_uom": "Nos",
    "item_name": "Television",
    "opening_qty": 190,
    "opening_val": 71250,
    "opening_fifo_queue": [],
    "in_qty": 0,
    "in_val": 0,
    "out_qty": 0,
    "out_val": 0,
    "bal_qty": 190,
    "bal_val": 71250,
    "val_rate": 375,
    "reserved_stock": 0
  },
  {
    "item_code": "SKU006",
    "warehouse": "Goods In Transit - FCD",
    "item_group": "Demo Item Group",
    "company": "Fashion Company (Demo)",
    "currency": 0,
    "stock_uom": "Nos",
    "item_name": "Coffee Mug",
    "opening_qty": 250,
    "opening_val": 105000,
    "opening_fifo_queue": [],
    "in_qty": 0,
    "in_val": 0,
    "out_qty": 0,
    "out_val": 0,
    "bal_qty": 250,
    "bal_val": 105000,
    "val_rate": 420,
    "reserved_stock": 0
  },
  {
    "item_code": "SKU008",
    "warehouse": "Stores - FCD",
    "item_group": "Demo Item Group",
    "company": "Fashion Company (Demo)",
    "currency": 0,
    "stock_uom": "Nos",
    "item_name": "Backpack",
    "opening_qty": 121,
    "opening_val": 40293,
    "opening_fifo_queue": [],
    "in_qty": 0,
    "in_val": 0,
    "out_qty": 0,
    "out_val": 0,
    "bal_qty": 121,
    "bal_val": 40293,
    "val_rate": 333,
    "reserved_stock": 0
  },
  {
    "item_code": "SKU008",
    "warehouse": "Finished Goods - FCD",
    "item_group": "Demo Item Group",
    "company": "Fashion Company (Demo)",
    "currency": 0,
    "stock_uom": "Nos",
    "item_name": "Backpack",
    "opening_qty": -20,
    "opening_val": -6660,
    "opening_fifo_queue": [],
    "in_qty": 0,
    "in_val": 0,
    "out_qty": 0,
    "out_val": 0,
    "bal_qty": -20,
    "bal_val": -6660,
    "val_rate": 333,
    "reserved_stock": 0
  },
  {
    "item_code": "SKU009",
    "warehouse": "Finished Goods - FCD",
    "item_group": "Demo Item Group",
    "company": "Fashion Company (Demo)",
    "currency": 0,
    "stock_uom": "Nos",
    "item_name": "Headphones",
    "opening_qty": -40,
    "opening_val": -28000,
    "opening_fifo_queue": [],
    "in_qty": 0,
    "in_val": 0,
    "out_qty": 0,
    "out_val": 0,
    "bal_qty": -40,
    "bal_val": -28000,
    "val_rate": 700,
    "reserved_stock": 0
  },
  {
    "item_code": "SKU001",
    "warehouse": "Finished Goods - FCD",
    "item_group": "Demo Item Group",
    "company": "Fashion Company (Demo)",
    "currency": 0,
    "stock_uom": "Nos",
    "item_name": "T-shirt",
    "opening_qty": 0,
    "opening_val": 0,
    "opening_fifo_queue": [],
    "in_qty": 0,
    "in_val": 0,
    "out_qty": 25,
    "out_val": 10000,
    "bal_qty": -25,
    "bal_val": -10000,
    "val_rate": 400,
    "reserved_stock": 0
  },
  {
    "item_code": "SKU002",
    "warehouse": "Finished Goods - FCD",
    "item_group": "Demo Item Group",
    "company": "Fashion Company (Demo)",
    "currency": 0,
    "stock_uom": "Nos",
    "item_name": "Laptop",
    "opening_qty": 0,
    "opening_val": 0,
    "opening_fifo_queue": [],
    "in_qty": 0,
    "in_val": 0,
    "out_qty": 15,
    "out_val": 4500,
    "bal_qty": -15,
    "bal_val": -4500,
    "val_rate": 300,
    "reserved_stock": 0
  },
  {
    "item_code": "SKU004",
    "warehouse": "Work In Progress - FCD",
    "item_group": "Demo Item Group",
    "company": "Fashion Company (Demo)",
    "currency": 0,
    "stock_uom": "Nos",
    "item_name": "Smartphone",
    "opening_qty": 0,
    "opening_val": 0,
    "opening_fifo_queue": [],
    "in_qty": 0,
    "in_val": 0,
    "out_qty": 20,
    "out_val": 14500,
    "bal_qty": -20,
    "bal_val": -14500,
    "val_rate": 725,
    "reserved_stock": 0
  },
  {
    "item_code": "SKU003",
    "warehouse": "Stores - FCD",
    "item_group": "Demo Item Group",
    "company": "Fashion Company (Demo)",
    "currency": 0,
    "stock_uom": "Nos",
    "item_name": "Book",
    "opening_qty": 0,
    "opening_val": 0,
    "opening_fifo_queue": [],
    "in_qty": 0,
    "in_val": 0,
    "out_qty": 100,
    "out_val": 52300,
    "bal_qty": -100,
    "bal_val": -52300,
    "val_rate": 523,
    "reserved_stock": 0
  },
  {
    "item_code": "SKU006",
    "warehouse": "Stores - FCD",
    "item_group": "Demo Item Group",
    "company": "Fashion Company (Demo)",
    "currency": 0,
    "stock_uom": "Nos",
    "item_name": "Coffee Mug",
    "opening_qty": 0,
    "opening_val": 0,
    "opening_fifo_queue": [],
    "in_qty": 0,
    "in_val": 0,
    "out_qty": 100,
    "out_val": 42000,
    "bal_qty": -100,
    "bal_val": -42000,
    "val_rate": 420,
    "reserved_stock": 0
  },
  {
    "item_code": "SKU007",
    "warehouse": "Stores - FCD",
    "item_group": "Demo Item Group",
    "company": "Fashion Company (Demo)",
    "currency": 0,
    "stock_uom": "Nos",
    "item_name": "Television",
    "opening_qty": 0,
    "opening_val": 0,
    "opening_fifo_queue": [],
    "in_qty": 0,
    "in_val": 0,
    "out_qty": 100,
    "out_val": 37500,
    "bal_qty": -100,
    "bal_val": -37500,
    "val_rate": 375,
    "reserved_stock": 0
  },
  {
    "item_code": "SKU005",
    "warehouse": "Stores - FCD",
    "item_group": "Demo Item Group",
    "company": "Fashion Company (Demo)",
    "currency": 0,
    "stock_uom": "Nos",
    "item_name": "Sneakers",
    "opening_qty": 0,
    "opening_val": 0,
    "opening_fifo_queue": [],
    "in_qty": 0,
    "in_val": 0,
    "out_qty": 150,
    "out_val": 33300,
    "bal_qty": -150,
    "bal_val": -33300,
    "val_rate": 222,
    "reserved_stock": 0
  },
  {
    "item_code": "SKU0101",
    "warehouse": "Outlets - FCD",
    "item_group": "Leathers X",
    "company": "Fashion Company (Demo)",
    "currency": 0,
    "stock_uom": "Nos",
    "item_name": "Sneakers",
    "opening_qty": 0,
    "opening_val": 0,
    "opening_fifo_queue": [],
    "in_qty": 10,
    "in_val": 0,
    "out_qty": 150,
    "out_val": 33300,
    "bal_qty": -150,
    "bal_val": -33300,
    "val_rate": 222,
    "reserved_stock": 0
  },
  {
    "item_code": "SKU0101",
    "warehouse": "Outlets - FCD",
    "item_group": "Leathers X",
    "company": "Fashion Company (Demo)",
    "currency": 0,
    "stock_uom": "Nos",
    "item_name": "Sneakers",
    "opening_qty": 0,
    "opening_val": 0,
    "opening_fifo_queue": [],
    "in_qty": 10,
    "in_val": 0,
    "out_qty": 0,
    "out_val": 33300,
    "bal_qty": -150,
    "bal_val": -33300,
    "val_rate": 222,
    "reserved_stock": 0
  },
  {
    "item_code": "SKU0101",
    "warehouse": "Outlets - FCD",
    "item_group": "Leathers X",
    "company": "Fashion Company (Demo)",
    "currency": 0,
    "stock_uom": "Nos",
    "item_name": "Sneakers",
    "opening_qty": 0,
    "opening_val": 0,
    "opening_fifo_queue": [],
    "in_qty": 0,
    "in_val": 0,
    "out_qty": 5,
    "out_val": 33300,
    "bal_qty": -150,
    "bal_val": -33300,
    "val_rate": 222,
    "reserved_stock": 0
  },
  {
    "item_code": "SKU0102",
    "warehouse": "Outlets - FCD",
    "item_group": "Leathers X",
    "company": "Fashion Company (Demo)",
    "currency": 0,
    "stock_uom": "Nos",
    "item_name": "Sneakers",
    "opening_qty": 0,
    "opening_val": 0,
    "opening_fifo_queue": [],
    "in_qty": 0,
    "in_val": 0,
    "out_qty": 90,
    "out_val": 33300,
    "bal_qty": -150,
    "bal_val": -33300,
    "val_rate": 222,
    "reserved_stock": 0
  },
  {
    "item_code": "SKU0103",
    "warehouse": "Outlets - FCD",
    "item_group": "Leathers Y",
    "company": "Fashion Company (Demo)",
    "currency": 0,
    "stock_uom": "Nos",
    "item_name": "Article 56",
    "opening_qty": 0,
    "opening_val": 0,
    "opening_fifo_queue": [],
    "in_qty": 100,
    "in_val": 0,
    "out_qty": 0,
    "out_val": 33300,
    "bal_qty": -150,
    "bal_val": -33300,
    "val_rate": 222,
    "reserved_stock": 0
  },
  {
    "item_code": "SKU0103",
    "warehouse": "Outlets - FCD",
    "item_group": "Leathers Y",
    "company": "Fashion Company (Demo)",
    "currency": 0,
    "stock_uom": "Nos",
    "item_name": "Article 56",
    "opening_qty": 0,
    "opening_val": 0,
    "opening_fifo_queue": [],
    "in_qty": 0,
    "in_val": 10,
    "out_qty": 50,
    "out_val": 33300,
    "bal_qty": -150,
    "bal_val": -33300,
    "val_rate": 222,
    "reserved_stock": 0
  }
]